requests_ai_validator/__init__.py
requests_ai_validator/functions.py
requests_ai_validator/core/__init__.py
requests_ai_validator/core/response.py
requests_ai_validator/core/session.py
requests_ai_validator/providers/__init__.py
requests_ai_validator/providers/anthropic_provider.py
requests_ai_validator/providers/base.py
requests_ai_validator/providers/factory.py
requests_ai_validator/providers/ollama_provider.py
requests_ai_validator/providers/openai_provider.py
requests_ai_validator/schemas/__init__.py
requests_ai_validator/schemas/base.py
requests_ai_validator/schemas/factory.py
requests_ai_validator/schemas/json_schema.py
requests_ai_validator/schemas/openapi_schema.py
requests_ai_validator/schemas/pydantic_schema.py
requests_ai_validator/utils/__init__.py
requests_ai_validator/utils/config.py
requests_ai_validator-1.1.1.dist-info/LICENSE
requests_ai_validator-1.1.1.dist-info/METADATA
requests_ai_validator-1.1.1.dist-info/WHEEL
requests_ai_validator-1.1.1.dist-info/top_level.txt
requests_ai_validator-1.1.1.dist-info/RECORD
