Metadata-Version: 2.1
Name: requests-ai-validator
Version: 1.1.1
Summary: AI-powered validation wrapper for Python requests library
Home-page: https://github.com/manikosto/requests-ai-validator
Author: Aleksei Koledachkin
Author-email: Aleksei Koledachkin <akoledachkin@gmail.com>
License: MIT
Project-URL: Homepage, https://github.com/manikosto/requests-ai-validator
Project-URL: Bug Reports, https://github.com/manikosto/requests-ai-validator/issues
Project-URL: Source, https://github.com/manikosto/requests-ai-validator
Project-URL: Documentation, https://github.com/manikosto/requests-ai-validator#readme
Keywords: requests,api,testing,validation,ai,http,automation
Classifier: Development Status :: 4 - Beta
Classifier: Intended Audience :: Developers
Classifier: License :: OSI Approved :: MIT License
Classifier: Operating System :: OS Independent
Classifier: Programming Language :: Python :: 3
Classifier: Programming Language :: Python :: 3.8
Classifier: Programming Language :: Python :: 3.9
Classifier: Programming Language :: Python :: 3.10
Classifier: Programming Language :: Python :: 3.11
Classifier: Programming Language :: Python :: 3.12
Classifier: Topic :: Software Development :: Testing
Classifier: Topic :: Internet :: WWW/HTTP
Classifier: Topic :: Scientific/Engineering :: Artificial Intelligence
Requires-Python: >=3.8
License-File: LICENSE
Requires-Dist: requests>=2.25.0
Requires-Dist: typing-extensions>=4.0.0
Provides-Extra: all
Requires-Dist: openai>=1.0.0; extra == "all"
Requires-Dist: anthropic>=0.25.0; extra == "all"
Requires-Dist: pydantic>=2.0.0; extra == "all"
Requires-Dist: jsonschema>=4.0.0; extra == "all"
Requires-Dist: PyYAML>=6.0; extra == "all"
Requires-Dist: allure-pytest>=2.12.0; extra == "all"
Provides-Extra: allure
Requires-Dist: allure-pytest>=2.12.0; extra == "allure"
Provides-Extra: anthropic
Requires-Dist: anthropic>=0.25.0; extra == "anthropic"
Provides-Extra: dev
Requires-Dist: pytest>=7.0.0; extra == "dev"
Requires-Dist: black>=22.0.0; extra == "dev"
Requires-Dist: flake8>=4.0.0; extra == "dev"
Requires-Dist: mypy>=1.0.0; extra == "dev"
Provides-Extra: jsonschema
Requires-Dist: jsonschema>=4.0.0; extra == "jsonschema"
Provides-Extra: openai
Requires-Dist: openai>=1.0.0; extra == "openai"
Provides-Extra: pydantic
Requires-Dist: pydantic>=2.0.0; extra == "pydantic"
Provides-Extra: yaml
Requires-Dist: PyYAML>=6.0; extra == "yaml"
